iframe_whitelist/__init__.py
iframe_whitelist/_version.py
iframe_whitelist-1.0.0.data/data/share/jupyter/labextensions/iframe-whitelist/package.json
iframe_whitelist-1.0.0.data/data/share/jupyter/labextensions/iframe-whitelist/static/347.4d6a87f276e6b41d1a51.js
iframe_whitelist-1.0.0.data/data/share/jupyter/labextensions/iframe-whitelist/static/445.a5c50857051297ec726d.js
iframe_whitelist-1.0.0.data/data/share/jupyter/labextensions/iframe-whitelist/static/7.2cf0ffd115525f39b856.js
iframe_whitelist-1.0.0.data/data/share/jupyter/labextensions/iframe-whitelist/static/728.1bb3b2d658d7b7ec3a03.js
iframe_whitelist-1.0.0.data/data/share/jupyter/labextensions/iframe-whitelist/static/728.1bb3b2d658d7b7ec3a03.js.LICENSE.txt
iframe_whitelist-1.0.0.data/data/share/jupyter/labextensions/iframe-whitelist/static/remoteEntry.f0fa2914f5c1db36b0a9.js
iframe_whitelist-1.0.0.data/data/share/jupyter/labextensions/iframe-whitelist/static/style.js
iframe_whitelist-1.0.0.data/data/share/jupyter/labextensions/iframe-whitelist/static/third-party-licenses.json
iframe_whitelist-1.0.0.data/data/share/jupyter/labextensions/iframe-whitelist/install.json
iframe_whitelist-1.0.0.dist-info/METADATA
iframe_whitelist-1.0.0.dist-info/WHEEL
iframe_whitelist-1.0.0.dist-info/licenses/LICENSE
iframe_whitelist-1.0.0.dist-info/RECORD
