Metadata-Version: 2.3
Name: iframe_whitelist
Version: 1.0.0
Dynamic: Keywords
Summary: Embed iframes in Markdown cells for authorised domains.
Project-URL: Homepage, https://gricad-gitlab.univ-grenoble-alpes.fr/doors/jupyterlab-iframe-whitelist
Project-URL: Bug Tracker, https://gricad-gitlab.univ-grenoble-alpes.fr/doors/jupyterlab-iframe-whitelist/issues
Project-URL: Repository, https://gricad-gitlab.univ-grenoble-alpes.fr/doors/jupyterlab-iframe-whitelist.git
Author-email: Calvin Massonnet Turner <calvin.massonnet@univ-grenoble-alpes.fr>
License: BSD 3-Clause License
License-File: LICENSE
Classifier: Framework :: Jupyter
Classifier: Framework :: Jupyter :: JupyterLab
Classifier: Framework :: Jupyter :: JupyterLab :: 4
Classifier: Framework :: Jupyter :: JupyterLab :: Extensions
Classifier: Framework :: Jupyter :: JupyterLab :: Extensions :: Prebuilt
Classifier: License :: OSI Approved :: BSD License
Classifier: Programming Language :: Python
Classifier: Programming Language :: Python :: 3
Classifier: Programming Language :: Python :: 3.8
Classifier: Programming Language :: Python :: 3.9
Classifier: Programming Language :: Python :: 3.10
Classifier: Programming Language :: Python :: 3.11
Classifier: Programming Language :: Python :: 3.12
Requires-Python: >=3.8
